MANIFEST.in
README.md
requirements.txt
setup.cfg
setup.py
examples/__init__.py
examples/account_methods.py
examples/direct_message_methods.py
examples/favorite_methods.py
examples/friendship_methods.py
examples/keys.py
examples/list_methods.py
examples/properties.py
examples/saved_search_methods.py
examples/status_methods.py
examples/timeline_methods.py
examples/trends_methods.py
examples/underlying_client.py
examples/user_methods.py
twitterpandas/__init__.py
twitterpandas/client.py
twitterpandas.egg-info/PKG-INFO
twitterpandas.egg-info/SOURCES.txt
twitterpandas.egg-info/dependency_links.txt
twitterpandas.egg-info/requires.txt
twitterpandas.egg-info/top_level.txt