Metadata-Version: 1.1
Name: twitterpandas
Version: 0.0.1
Summary: A library for getting and interacting with twitter data via pandas
Home-page: https://github.com/wdm0006/twitterpandas
Author: Will McGinnis
Author-email: will@pedalwrencher.com
License: BSD
Download-URL: https://github.com/wdm0006/twitterpandas/tarball/0.0.1
Platform: UNKNOWN
Classifier: Development Status :: 3 - Alpha
Classifier: Intended Audience :: Developers
Classifier: Programming Language :: Python :: 3
